wd14_tagger_api/__init__.py
wd14_tagger_api/__main__.py
wd14_tagger_api/server.py
wd14_tagger_api/wd14_tagger.py
wd14_tagger_api/tagger/dbimutils.py
wd14_tagger_api/tagger/image.py
wd14_tagger_api/tagger/interrogator.py
wd14_tagger_api/tagger/interrogators.py
wd14_tagger_api-0.0.1.dist-info/METADATA
wd14_tagger_api-0.0.1.dist-info/WHEEL
wd14_tagger_api-0.0.1.dist-info/licenses/LICENSE
wd14_tagger_api-0.0.1.dist-info/RECORD
