Metadata-Version: 2.1
Name: wd14-tagger-api
Version: 0.0.1
Summary: A simple FastAPI server to host WD14 Tagger
Project-URL: Homepage, https://github.com/daswer123/wd14-tagger-api-server
Project-URL: Bug Tracker, https://github.com/daswer123/wd14-tagger-api-server/issues
Author-email: daswer123 <daswerq123@gmail.com>
License-File: LICENSE
Classifier: License :: OSI Approved :: MIT License
Classifier: Operating System :: OS Independent
Classifier: Programming Language :: Python :: 3
Requires-Python: >=3.9
Requires-Dist: deepdanbooru==1.0.2
Requires-Dist: fastapi
Requires-Dist: huggingface-hub==0.17.3
Requires-Dist: onnxruntime==1.16.0
Requires-Dist: opencv-python==4.8.0.76
Requires-Dist: pandas==2.1.1
Requires-Dist: pillow==10.0.1
Requires-Dist: python-multipart
Requires-Dist: requests
Requires-Dist: torch>=2.0.1
Requires-Dist: uvicorn
